README.rst
setup.py
physdata/__init__.py
physdata/star.py
physdata/xray.py
physdata.egg-info/PKG-INFO
physdata.egg-info/SOURCES.txt
physdata.egg-info/dependency_links.txt
physdata.egg-info/entry_points.txt
physdata.egg-info/requires.txt
physdata.egg-info/top_level.txt