Metadata-Version: 1.1
Name: physdata
Version: 0.2.0
Summary: A python interface to some sources of physical data
Home-page: https://github.com/dih5/physdata
Author: Dih5
Author-email: guillehg@gmail.com
License: LGPLv3+
Keywords: X-ray attenuation,Stopping power
Platform: UNKNOWN
Classifier: Development Status :: 4 - Beta
Classifier: Intended Audience :: Science/Research
Classifier: Topic :: Scientific/Engineering :: Physics
Classifier: License :: OSI Approved :: GNU Lesser General Public License v3 or later (LGPLv3+)
Classifier: Programming Language :: Python :: 2
Classifier: Programming Language :: Python :: 2.7
Classifier: Programming Language :: Python :: 3
Classifier: Programming Language :: Python :: 3.3
Classifier: Programming Language :: Python :: 3.4
Classifier: Programming Language :: Python :: 3.5
Classifier: Programming Language :: Python :: 3.6
